{
  "type": "tweet",
  "tweet_id": "1803597048593215826",
  "screen_name": "safizaq",
  "bookmarks": 0,
  "favorites": 3,
  "created_at": "Thu Jun 20 01:13:40 +0000 2024",
  "text": "Introducing... \n\nUmmahfy: a digital hub for muslims\n\ncc: @_buildspace https://t.co/MDMtnC0AwK",
  "lang": "in",
  "quotes": 0,
  "replies": 1,
  "conversation_id": "1803597048593215826",
  "retweets": 1,
  "views": "71",
  "user_info": {
    "screen_name": "safizaq",
    "name": "Safi Qadir",
    "description": "calligraphy artist & 2x attempted startup founder. sharing my insights as i build something new.",
    "rest_id": "1760665787621093376",
    "followers_count": 42,
    "favourites_count": 20,
    "avatar": "https://pbs.twimg.com/profile_images/1760675979134119936/9-0Q2Vwo_normal.jpg",
    "verified": false,
    "friends_count": 35
  },
  "media": {
    "photo": [
      {
        "media_url_https": "https://pbs.twimg.com/media/GQepgHqWAAAe-b8.jpg",
        "id": "1803596545062731776"
      }
    ]
  }
}