{
  "type": "tweet",
  "tweet_id": "1803885953565503599",
  "screen_name": "white54light",
  "bookmarks": 0,
  "favorites": 2,
  "created_at": "Thu Jun 20 20:21:40 +0000 2024",
  "text": "here we go\nTell me what y'all thinking?\nPoc: special thanks for @FarzaTV &amp; @_buildspace for this great experience \ncc: @_buildspace @_nightsweekends https://t.co/oduSihXXvw",
  "lang": "en",
  "quotes": 1,
  "replies": 4,
  "conversation_id": "1803885953565503599",
  "retweets": 0,
  "views": "100",
  "user_info": {
    "screen_name": "white54light",
    "name": "Silent Scream",
    "description": "Beautiful lifex0",
    "rest_id": "1483190850700165127",
    "followers_count": 48,
    "favourites_count": 16,
    "avatar": "https://pbs.twimg.com/profile_images/1483191159094751232/3HDUmj8K_normal.png",
    "verified": false,
    "friends_count": 81
  },
  "media": {
    "photo": [
      {
        "media_url_https": "https://pbs.twimg.com/media/GQiwtwgXAAACpWl.jpg",
        "id": "1803885950923112448"
      }
    ]
  }
}