{
  "type": "tweet",
  "tweet_id": "1803803680744874472",
  "screen_name": "negarvahid_",
  "bookmarks": 1,
  "favorites": 4,
  "created_at": "Thu Jun 20 14:54:45 +0000 2024",
  "text": "I've been sitting on this idea for 2 years. Why? Cuz I always ended up overthinking about its marketing or whatever. But who cares? I think it's cool. So fuck it I'm doing it this time. \n\nSuggestions, ideas, questions, etc?\ncc: @_nightsweekends, @_buildspace https://t.co/wpuRe1nLH8",
  "lang": "en",
  "quotes": 1,
  "replies": 3,
  "conversation_id": "1803803680744874472",
  "retweets": 1,
  "views": "112",
  "user_info": {
    "screen_name": "negarvahid_",
    "name": "Negar Vahid",
    "description": "Deep Learning Researcher, Quantum Computing Enthusiast, Masters student @ Istanbul Technical University",
    "rest_id": "818190291043749888",
    "followers_count": 81,
    "favourites_count": 4393,
    "avatar": "https://pbs.twimg.com/profile_images/1803801962502111233/DKDOzIrq_normal.jpg",
    "verified": false,
    "friends_count": 258
  },
  "media": {
    "photo": [
      {
        "media_url_https": "https://pbs.twimg.com/media/GQhkt1PWMAApYf4.jpg",
        "id": "1803802389310222336"
      }
    ]
  }
}