{
  "type": "tweet",
  "tweet_id": "1803431973416824837",
  "screen_name": "s1thsv",
  "bookmarks": 0,
  "favorites": 3,
  "created_at": "Wed Jun 19 14:17:43 +0000 2024",
  "text": "i travel quite a lot and maintain an instagram page https://t.co/JanXffCi8a to share tips and stories. \n\nWhen i'm travelling, it's sometimes cumbersome to organise and retrieve travel documents. I plan to solve this with JetSetTravel \n\ncc @_buildspace https://t.co/sDR0w7OieZ",
  "lang": "en",
  "quotes": 1,
  "replies": 4,
  "conversation_id": "1803431973416824837",
  "retweets": 1,
  "views": "163",
  "user_info": {
    "screen_name": "s1thsv",
    "name": "yeswanth",
    "description": "💻 Technologist (Freelance + CTO @ a fintech startup) \n🎒 Travelling with @sunnyash_travel \n⚡️Jack of all trades, master of a few\n🎓 Fellow @StoaHQ",
    "rest_id": "123015239",
    "followers_count": 458,
    "favourites_count": 881,
    "avatar": "https://pbs.twimg.com/profile_images/982093338139492353/LAl_9IBC_normal.jpg",
    "verified": false,
    "friends_count": 845
  },
  "media": {
    "photo": [
      {
        "media_url_https": "https://pbs.twimg.com/media/GQcTriZWUAA32WE.jpg",
        "id": "1803431814473601024"
      }
    ]
  }
}