{
  "type": "tweet",
  "tweet_id": "1803527386211766292",
  "screen_name": "VictorGulchenko",
  "bookmarks": 0,
  "favorites": 5,
  "created_at": "Wed Jun 19 20:36:51 +0000 2024",
  "text": "Who submitted his first n&amp;w update already?\n\n@_nightsweekends @_buildspace https://t.co/4siJMq42CJ",
  "lang": "en",
  "quotes": 0,
  "replies": 0,
  "conversation_id": "1803527386211766292",
  "retweets": 0,
  "views": "71",
  "user_info": {
    "screen_name": "VictorGulchenko",
    "name": "Victor",
    "description": "17 years old | into #ai, #tech and #web3 |taking part at s5 n&w at @buildspace | Dream: move to San Francisco, searching for builders and creators",
    "rest_id": "1694244664235225088",
    "followers_count": 169,
    "favourites_count": 3910,
    "avatar": "https://pbs.twimg.com/profile_images/1695464448696147968/71LlWEmX_normal.jpg",
    "verified": false,
    "friends_count": 261
  },
  "media": {
    "photo": [
      {
        "media_url_https": "https://pbs.twimg.com/media/GQdqmOJWEAAn__3.jpg",
        "id": "1803527380650037248"
      }
    ]
  }
}