{
  "type": "tweet",
  "tweet_id": "1803827444996075553",
  "screen_name": "Noxx_Art",
  "bookmarks": 3,
  "favorites": 6,
  "created_at": "Thu Jun 20 16:29:11 +0000 2024",
  "text": "This has been on my mind for so long.\n\nIt has been a while since I posted here.\n\nWhat better way to start again\nwith something productive. 🦾\n\n@_nightsweekends @_buildspace https://t.co/XKZfYcUh4I",
  "lang": "en",
  "quotes": 0,
  "replies": 4,
  "conversation_id": "1803827444996075553",
  "retweets": 0,
  "views": "186",
  "user_info": {
    "screen_name": "Noxx_Art",
    "name": "Noxx",
    "description": "3D Artist | Designer | Mentor - Discovering what lies beyond my own imaginary limitations and taking you with me.\n- https://t.co/iz97cHS7SY - https://t.co/BDqUpToDFL",
    "rest_id": "1358390431248220165",
    "followers_count": 7605,
    "favourites_count": 15622,
    "avatar": "https://pbs.twimg.com/profile_images/1439515854635470851/7tV12DpF_normal.jpg",
    "verified": false,
    "friends_count": 889
  },
  "media": {
    "photo": [
      {
        "media_url_https": "https://pbs.twimg.com/media/GQh7F-PXcAQ5qcS.jpg",
        "id": "1803826993298894852"
      }
    ]
  }
}