{
  "type": "tweet",
  "tweet_id": "1803149012129947978",
  "screen_name": "coderhema",
  "bookmarks": 20,
  "favorites": 347,
  "created_at": "Tue Jun 18 19:33:20 +0000 2024",
  "text": "\"Job searching by swiping right\"\n\nmight look like the most generic project idea, but till day 60 🤲🏾\n\ncc @_buildspace  @_nightsweekends https://t.co/wmjwpw6P5w",
  "lang": "en",
  "quotes": 3,
  "replies": 186,
  "conversation_id": "1803149012129947978",
  "retweets": 7,
  "views": "11318",
  "user_info": {
    "screen_name": "coderhema",
    "name": "Olugbemi Opedepodepes",
    "description": "I am a Brand Designer | Pythonista and AI Enthusiasts | building B00ls | Flickkegigs |AI Partner @Freepik ✦ \nlink: https://t.co/JWoEuI93Dq",
    "rest_id": "1413810915401740290",
    "followers_count": 323,
    "favourites_count": 6332,
    "avatar": "https://pbs.twimg.com/profile_images/1802998883817000961/b3IQa881_normal.jpg",
    "verified": false,
    "friends_count": 1462
  },
  "media": {
    "photo": [
      {
        "media_url_https": "https://pbs.twimg.com/media/GQYSSaPXkAEGsAP.jpg",
        "id": "1803148808299188225"
      }
    ]
  }
}