{
  "type": "tweet",
  "tweet_id": "1803848893878141425",
  "screen_name": "therafaelvarela",
  "bookmarks": 0,
  "favorites": 2,
  "created_at": "Thu Jun 20 17:54:24 +0000 2024",
  "text": "Here's my idea for s5 of @_nightsweekends @_buildspace \n\nWhat do you think? I'd love to hear your feedback https://t.co/JCrce0XcL9",
  "lang": "en",
  "quotes": 0,
  "replies": 1,
  "conversation_id": "1803848893878141425",
  "retweets": 0,
  "views": "23",
  "user_info": {
    "screen_name": "therafaelvarela",
    "name": "Rafa",
    "description": "Software Developer",
    "rest_id": "88116288",
    "followers_count": 33,
    "favourites_count": 272,
    "avatar": "https://pbs.twimg.com/profile_images/1722065744622489600/NFg4XgbG_normal.jpg",
    "verified": false,
    "friends_count": 330
  },
  "media": {
    "photo": [
      {
        "media_url_https": "https://pbs.twimg.com/media/GQiOzzaXMAABiyQ.jpg",
        "id": "1803848671387136000"
      }
    ]
  }
}