{
  "type": "tweet",
  "tweet_id": "1803597498193215664",
  "screen_name": "DeepManuPy",
  "bookmarks": 0,
  "favorites": 6,
  "created_at": "Thu Jun 20 01:15:27 +0000 2024",
  "text": "Excited to be collaborating with @nrenjiofficial in @_nightsweekends S5! 🚀\nStay tuned for updates as we bring this innovative idea to life! #ai #systemdesign #nightsandweekends #s5\n@_buildspace https://t.co/PEjmgleUj7",
  "lang": "en",
  "quotes": 0,
  "replies": 6,
  "conversation_id": "1803597498193215664",
  "retweets": 0,
  "views": "137",
  "user_info": {
    "screen_name": "DeepManuPy",
    "name": "Manudeep Reddy",
    "description": "",
    "rest_id": "1084698207479771136",
    "followers_count": 19,
    "favourites_count": 792,
    "avatar": "https://pbs.twimg.com/profile_images/1234176107890364416/J7bHmyDM_normal.jpg",
    "verified": false,
    "friends_count": 44
  },
  "media": {
    "photo": [
      {
        "media_url_https": "https://pbs.twimg.com/media/GQeoLzcWYAEKY3P.png",
        "id": "1803595096526315521"
      }
    ]
  }
}