{
  "type": "tweet",
  "tweet_id": "1803891962807738687",
  "screen_name": "nabs0824",
  "bookmarks": 1,
  "favorites": 1,
  "created_at": "Thu Jun 20 20:45:33 +0000 2024",
  "text": "Tried a few voice AI products and chose VAPI! Opted for RAG over fine-tune since it works as intended. Dataset is curated to handle high stress mental health calls for the Build Space community to call in and vent when overwhelmed.@_buildspace  @_nightsweekends #buildinginpublic https://t.co/ZWzqVpvwOW",
  "lang": "en",
  "quotes": 0,
  "replies": 0,
  "conversation_id": "1803891962807738687",
  "retweets": 0,
  "views": "50",
  "user_info": {
    "screen_name": "nabs0824",
    "name": "nabil",
    "description": "",
    "rest_id": "903779537225441280",
    "followers_count": 234,
    "favourites_count": 5737,
    "avatar": "https://pbs.twimg.com/profile_images/1737218594449010688/U6XU4Ulx_normal.jpg",
    "verified": false,
    "friends_count": 883
  },
  "media": {
    "photo": [
      {
        "media_url_https": "https://pbs.twimg.com/media/GQizex4XcAEzUoJ.jpg",
        "id": "1803888992129085441"
      }
    ]
  }
}