{
  "type": "tweet",
  "tweet_id": "1803981000822698145",
  "screen_name": "SeifShahinAi",
  "bookmarks": 0,
  "favorites": 5,
  "created_at": "Fri Jun 21 02:39:21 +0000 2024",
  "text": "a little ironic considering that I ran an Automation agency that used to layoff these workers at some point 💀\n\ncc: @_buildspace @_nightsweekends https://t.co/d1TelatJ7Q",
  "lang": "en",
  "quotes": 0,
  "replies": 1,
  "conversation_id": "1803981000822698145",
  "retweets": 1,
  "views": "49",
  "user_info": {
    "screen_name": "SeifShahinAi",
    "name": "Seif Shahin",
    "description": "",
    "rest_id": "1723632462650015744",
    "followers_count": 2,
    "favourites_count": 83,
    "avatar": "https://pbs.twimg.com/profile_images/1739309057821786112/1iNd4BK7_normal.jpg",
    "verified": false,
    "friends_count": 9
  },
  "media": {
    "photo": [
      {
        "media_url_https": "https://pbs.twimg.com/media/GQkHI48X0AAr7Io.jpg",
        "id": "1803980975044546560"
      }
    ]
  }
}