{
  "type": "tweet",
  "tweet_id": "1803809355386531929",
  "screen_name": "trezi29",
  "bookmarks": 0,
  "favorites": 4,
  "created_at": "Thu Jun 20 15:17:18 +0000 2024",
  "text": "I know I will never make any money from this, but I always loved the idea of working on something bike related.\n\nIt'll be my little fun side project, and hopefully I'll learn something and meet cool people along the way!\n\ncc: @_buildspace @_nightsweekends https://t.co/8Ql6FjeifN",
  "lang": "en",
  "quotes": 0,
  "replies": 3,
  "conversation_id": "1803809355386531929",
  "retweets": 0,
  "views": "81",
  "user_info": {
    "screen_name": "trezi29",
    "name": "Trezi",
    "description": "31/12/2023 I quit my job because I could not stand it anymore.\n\nThis profile serves as my journal from that moment on.",
    "rest_id": "96774557",
    "followers_count": 30,
    "favourites_count": 587,
    "avatar": "https://pbs.twimg.com/profile_images/1652311598583754752/jOPTj6m3_normal.jpg",
    "verified": false,
    "friends_count": 259
  },
  "media": {
    "photo": [
      {
        "media_url_https": "https://pbs.twimg.com/media/GQhqyCLW0AASkhM.jpg",
        "id": "1803809058572390400"
      }
    ]
  }
}