{
  "type": "tweet",
  "tweet_id": "1803888254481031575",
  "screen_name": "zeniarangwala",
  "bookmarks": 0,
  "favorites": 4,
  "created_at": "Thu Jun 20 20:30:49 +0000 2024",
  "text": "In our fast-paced world, financial literacy is crucial. KidCash, a fun banking app for kids, turns saving into a playful adventure. \"Do not save what is left after spending, but spend what is left after saving.\" - Warren Buffett. cc: @_buildspace @_nightsweekends https://t.co/eS6FsbHuRN",
  "lang": "en",
  "quotes": 0,
  "replies": 4,
  "conversation_id": "1803888254481031575",
  "retweets": 0,
  "views": "101",
  "user_info": {
    "screen_name": "zeniarangwala",
    "name": "zeniarangwalaa",
    "description": "Design @uwaterloo🎨🎓✨",
    "rest_id": "2260625809",
    "followers_count": 53,
    "favourites_count": 1130,
    "avatar": "https://pbs.twimg.com/profile_images/1803900480692596736/oP0cR6xe_normal.jpg",
    "verified": false,
    "friends_count": 169
  },
  "media": {
    "photo": [
      {
        "media_url_https": "https://pbs.twimg.com/media/GQixMc8WQAAY5t-.png",
        "id": "1803886478247739392"
      }
    ]
  }
}