{
  "type": "tweet",
  "tweet_id": "1804075061013348839",
  "screen_name": "plocksdev",
  "bookmarks": 0,
  "favorites": 3,
  "created_at": "Fri Jun 21 08:53:07 +0000 2024",
  "text": "I joined s4 of @_nightsweekends but gave up midway (mental burnout). \n\nBut I'm back and this time with more resilience and determination. \n\nthis time, I am building a simple tool to organize your files n' folders based on custom user categories.\n\n@_buildspace https://t.co/kl5EKyfoyU",
  "lang": "en",
  "quotes": 0,
  "replies": 0,
  "conversation_id": "1804075061013348839",
  "retweets": 0,
  "views": "20",
  "user_info": {
    "screen_name": "plocksdev",
    "name": "plocks",
    "description": "nights and weekends s5\n\ncurrently building: computer file organizer",
    "rest_id": "1689007128898383872",
    "followers_count": 14,
    "favourites_count": 33,
    "avatar": "https://pbs.twimg.com/profile_images/1689018216536784896/ygCLvV4c_normal.jpg",
    "verified": false,
    "friends_count": 10
  },
  "media": {
    "photo": [
      {
        "media_url_https": "https://pbs.twimg.com/media/GQlcQIgXoAAVAjD.jpg",
        "id": "1804074557969506304"
      }
    ]
  }
}